Packages/__init__.py
Packages/my_module.py
GoktugTest-0.1.0.dist-info/LICENSE
GoktugTest-0.1.0.dist-info/METADATA
GoktugTest-0.1.0.dist-info/WHEEL
GoktugTest-0.1.0.dist-info/top_level.txt
GoktugTest-0.1.0.dist-info/RECORD
